ayda_tools/__init__.py
ayda_tools/data.py
ayda_tools/interfaces.py
ayda_tools/parsing.py
ayda_tools/client/__init__.py
ayda_tools/client/callbacks.py
ayda_tools/client/clientservice.py
ayda_tools/client/connection.py
ayda_tools/client/resultservice.py
ayda_tools/client/run_client.py
ayda_tools/client/systemstats.py
ayda_tools/client/trainingservice.py
ayda_tools-0.6.0.data/scripts/ayda_client
ayda_tools-0.6.0.data/scripts/ayda_parse
test/__init__.py
test/test_connection.py
test/test_logging.py
test/test_runclient.py
test/test_systemstats.py
test/test_training.py
ayda_tools-0.6.0.dist-info/METADATA
ayda_tools-0.6.0.dist-info/WHEEL
ayda_tools-0.6.0.dist-info/top_level.txt
ayda_tools-0.6.0.dist-info/RECORD
