Metadata-Version: 2.1
Name: ayda-tools
Version: 0.6.0
Summary: A  for Data Analysis
Author: Christian Bodenstein
Author-email: bodenstein@soccerwatch.tv
Requires-Dist: jsonpickle
Requires-Dist: requests
Requires-Dist: docstring-parser
Requires-Dist: gpuinfo
Requires-Dist: psutil
Requires-Dist: numpy
Requires-Dist: google-cloud-storage
Requires-Dist: python-dateutil
